bitcoin_rpcpy/__init__.py
bitcoin_rpcpy/bitcoin_rpc.py
bitcoin_rpcpy/chainstate.json
savingsatoshi_bitcoin_rpcpy-253.1.2.dist-info/METADATA
savingsatoshi_bitcoin_rpcpy-253.1.2.dist-info/WHEEL
savingsatoshi_bitcoin_rpcpy-253.1.2.dist-info/RECORD
