Metadata-Version: 2.1
Name: savingsatoshi_bitcoin_rpcpy
Version: 253.1.2
Summary: faux bitcoin core for Saving Satoshi code challenges
License: MIT
Author: Matthew Zipkin
Author-email: pinheadmz@gmail.com
Requires-Python: >=3.11,<4.0
Classifier: License :: OSI Approved :: MIT License
Classifier: Programming Language :: Python :: 3
Classifier: Programming Language :: Python :: 3.11
Classifier: Programming Language :: Python :: 3.12
